<?xml version="1.0"?>
<!DOCTYPE hibernate-mapping PUBLIC "-//Hibernate/Hibernate Mapping DTD 3.0//EN"
"http://hibernate.sourceforge.net/hibernate-mapping-3.0.dtd">

<hibernate-mapping>
	<class name="cn.gaily.crm.domain.SysRole" table="sys_role">
		<id name="id" type="string">
			<column name="id" sql-type="varchar(36)"/>
			<generator class="uuid"/>
		</id>
		<property name="remark" type="text">
			<column name="remark" sql-type="text"/>
		</property>
		<property name="name" type="string">
			<column name="name" sql-type="varchar(100)"/>
		</property>
	</class>
</hibernate-mapping>